pyevermizer/__init__.py
pyevermizer/_evermizer.cpython-313-x86_64-linux-gnu.so
pyevermizer-0.50.1.dist-info/METADATA
pyevermizer-0.50.1.dist-info/RECORD
pyevermizer-0.50.1.dist-info/top_level.txt
pyevermizer-0.50.1.dist-info/WHEEL
pyevermizer-0.50.1.dist-info/COPYING.LESSER
pyevermizer-0.50.1.dist-info/COPYING
