Metadata-Version: 2.2
Name: pyevermizer
Version: 0.50.1
Summary: Python wrapper for Evermizer
Home-page: https://github.com/black-sliver/pyevermizer
Author: black-sliver
License: LGPLv3
Requires-Python: >=3
License-File: COPYING
License-File: COPYING.LESSER
Dynamic: author
Dynamic: description
Dynamic: description-content-type
Dynamic: home-page
Dynamic: license
Dynamic: requires-python
Dynamic: summary
